blurhash_numba/__init__.py
blurhash_numba/blurhash.py
blurhash_numba/version.py
blurhash_numba-0.0.1.dist-info/LICENSE
blurhash_numba-0.0.1.dist-info/METADATA
blurhash_numba-0.0.1.dist-info/WHEEL
blurhash_numba-0.0.1.dist-info/top_level.txt
blurhash_numba-0.0.1.dist-info/RECORD
