Metadata-Version: 2.1
Name: blurhash-numba
Version: 0.0.1
Summary: Numba aware BlurHash encoder and decoder implementation for Python
Home-page: https://realworldpython.guide/blurhash-numba/
Author: Ankit Mahato
Author-email: ankit@realworldpython.guide
License: UNKNOWN
Project-URL: Source Code, https://github.com/animator/blurhash-numba
Project-URL: Bug Tracker, https://github.com/animator/blurhash-numba/issues
Project-URL: Documentation, https://realworldpython.guide/blurhash-numba/
Keywords: blurhash python numba placeholder image
Platform: UNKNOWN
Classifier: Development Status :: 5 - Production/Stable
Classifier: Intended Audience :: Developers
Classifier: Intended Audience :: Information Technology
Classifier: Topic :: Software Development
Classifier: Topic :: Software Development :: Libraries
Classifier: Topic :: Software Development :: Libraries :: Python Modules
Classifier: License :: OSI Approved :: MIT License
Classifier: Operating System :: OS Independent
Classifier: Programming Language :: Python :: 3 :: Only
Classifier: Programming Language :: Python :: 3
Classifier: Programming Language :: Python :: 3.6
Classifier: Programming Language :: Python :: 3.7
Classifier: Programming Language :: Python :: 3.8
Classifier: Natural Language :: English
Requires-Python: >=3.6
Requires-Dist: numba (>=0.51.0)
Provides-Extra: pillow
Requires-Dist: Pillow (>=7.2.0) ; extra == 'pillow'
Provides-Extra: testing
Requires-Dist: pytest ; extra == 'testing'
Requires-Dist: Pillow (>=7.2.0) ; extra == 'testing'
